graphxl/__init__.py
graphxl/data.py
graphxl/embeddings_analysis.py
graphxl/experiment_handlers.py
graphxl/features.py
graphxl/graph_build.py
graphxl/graphlet_builds.py
graphxl/inference.py
graphxl/local_config.py
graphxl/logging_setup.py
graphxl/mlflow_client_.py
graphxl/models.py
graphxl/node_state_features.py
graphxl/plotly_helpers.py
graphxl/train.py
graphxl/training_eval_anime.py
graphxl/transform.py
graphxl/utils.py
graphxl/version.py
graphxl-0.1.0.dist-info/METADATA
graphxl-0.1.0.dist-info/WHEEL
graphxl-0.1.0.dist-info/RECORD
