Metadata-Version: 2.1
Name: graphxl
Version: 0.1.0
Summary: Workbench for Deep Learning on network datasets
Author: ybangaru
Author-email: yaswanthbangaru13@gmail.com
Requires-Python: >=3.8,<4.0
Classifier: Programming Language :: Python :: 3
Classifier: Programming Language :: Python :: 3.8
Classifier: Programming Language :: Python :: 3.9
Classifier: Programming Language :: Python :: 3.10
Classifier: Programming Language :: Python :: 3.11
Classifier: Programming Language :: Python :: 3.12
Requires-Dist: dash (>=2.15.0,<3.0.0)
Requires-Dist: geopandas (==0.13.2)
Requires-Dist: kaleido (==0.2.1)
Requires-Dist: mlflow (>=2.10.2,<3.0.0)
Requires-Dist: opencv-python (>=4.9.0.80,<5.0.0.0)
Requires-Dist: pandas (==1.4.4)
Requires-Dist: plotly (>=5.19.0,<6.0.0)
Requires-Dist: rtree (>=1.2.0,<2.0.0)
Requires-Dist: scanpy (>=1.9.8,<2.0.0)
Requires-Dist: shapely (>=2.0.3,<3.0.0)
Requires-Dist: squidpy (==1.2.2)
Requires-Dist: torch (>=1.13.0)
Requires-Dist: torch_geometric (>=2.2.0)
Requires-Dist: torchviz (>=0.0.2,<0.0.3)
